azure/eventhub/__init__.py
azure/eventhub/_client_base.py
azure/eventhub/_common.py
azure/eventhub/_configuration.py
azure/eventhub/_connection_manager.py
azure/eventhub/_connection_string_parser.py
azure/eventhub/_constants.py
azure/eventhub/_consumer.py
azure/eventhub/_consumer_client.py
azure/eventhub/_mixin.py
azure/eventhub/_producer.py
azure/eventhub/_producer_client.py
azure/eventhub/_tracing.py
azure/eventhub/_utils.py
azure/eventhub/_version.py
azure/eventhub/exceptions.py
azure/eventhub/py.typed
azure/eventhub/_buffered_producer/__init__.py
azure/eventhub/_buffered_producer/_buffered_producer.py
azure/eventhub/_buffered_producer/_buffered_producer_dispatcher.py
azure/eventhub/_buffered_producer/_partition_resolver.py
azure/eventhub/_eventprocessor/__init__.py
azure/eventhub/_eventprocessor/_eventprocessor_mixin.py
azure/eventhub/_eventprocessor/checkpoint_store.py
azure/eventhub/_eventprocessor/common.py
azure/eventhub/_eventprocessor/event_processor.py
azure/eventhub/_eventprocessor/in_memory_checkpoint_store.py
azure/eventhub/_eventprocessor/ownership_manager.py
azure/eventhub/_eventprocessor/partition_context.py
azure/eventhub/_pyamqp/__init__.py
azure/eventhub/_pyamqp/_connection.py
azure/eventhub/_pyamqp/_decode.py
azure/eventhub/_pyamqp/_encode.py
azure/eventhub/_pyamqp/_message_backcompat.py
azure/eventhub/_pyamqp/_platform.py
azure/eventhub/_pyamqp/_transport.py
azure/eventhub/_pyamqp/authentication.py
azure/eventhub/_pyamqp/cbs.py
azure/eventhub/_pyamqp/client.py
azure/eventhub/_pyamqp/constants.py
azure/eventhub/_pyamqp/endpoints.py
azure/eventhub/_pyamqp/error.py
azure/eventhub/_pyamqp/link.py
azure/eventhub/_pyamqp/management_link.py
azure/eventhub/_pyamqp/management_operation.py
azure/eventhub/_pyamqp/message.py
azure/eventhub/_pyamqp/outcomes.py
azure/eventhub/_pyamqp/performatives.py
azure/eventhub/_pyamqp/receiver.py
azure/eventhub/_pyamqp/sasl.py
azure/eventhub/_pyamqp/sender.py
azure/eventhub/_pyamqp/session.py
azure_eventhub-5.13.0.dist-info/LICENSE
azure_eventhub-5.13.0.dist-info/METADATA
azure_eventhub-5.13.0.dist-info/WHEEL
azure_eventhub-5.13.0.dist-info/top_level.txt
azure_eventhub-5.13.0.dist-info/RECORD
